grscheller/boring_math/__init__.py
grscheller/boring_math/integer_math.py
grscheller/boring_math/py.typed
grscheller/boring_math/pythag3.py
grscheller/boring_math/recursive.py
grscheller/boring_math/cli/__init__.py
grscheller/boring_math/cli/ackermann.py
grscheller/boring_math/cli/py.typed
grscheller/boring_math/cli/pythag3.py
grscheller/boring_math/distributions/__init__.py
grscheller/boring_math/distributions/datasets.py
grscheller/boring_math/distributions/distribution.py
grscheller/boring_math/distributions/py.typed
grscheller/boring_math/distributions/continuous/__init__.py
grscheller/boring_math/distributions/continuous/normal.py
grscheller/boring_math/distributions/continuous/py.typed
grscheller/boring_math/distributions/discrete/__init__.py
grscheller/boring_math/distributions/discrete/binomial.py
grscheller/boring_math/distributions/discrete/py.typed
grscheller_boring_math-0.4.9.dist-info/entry_points.txt
grscheller_boring_math-0.4.9.dist-info/LICENSE
grscheller_boring_math-0.4.9.dist-info/WHEEL
grscheller_boring_math-0.4.9.dist-info/METADATA
grscheller_boring_math-0.4.9.dist-info/RECORD
