Metadata-Version: 2.3
Name: grscheller.boring-math
Version: 0.4.9
Summary: ### Mathematical Libraries Package
Keywords: math,mathematics,lcm,gcd,primes,comb,combinations,pythagorean triples,ackermann,fibonacci
Author-email: "Geoffrey R. Scheller" <geoffrey@scheller.com>
Requires-Python: >=3.12
Classifier: Development Status :: 3 - Alpha
Classifier: Framework :: Pytest
Classifier: Intended Audience :: Developers
Classifier: Intended Audience :: Education
Classifier: Intended Audience :: Science/Research
Classifier: License :: OSI Approved :: Apache Software License
Classifier: Operating System :: OS Independent
Classifier: Programming Language :: Python :: 3.13
Classifier: Typing :: Typed
Requires-Dist: grscheller.circular-array >= 3.8.1, < 3.9
Requires-Dist: grscheller.fp >= 1.2.0, < 1.3
Requires-Dist: matplotlib >= 3.9
Requires-Dist: pytest >=8.3.2 ; extra == "tests"
Project-URL: Changelog, https://github.com/grscheller/boring-math/blob/main/CHANGELOG.md
Project-URL: Documentation, https://grscheller.github.io/grscheller-pypi-namespace-docs/boring-math
Project-URL: Source, https://github.com/grscheller/boring-math
Provides-Extra: tests
